setup.cfg
setup.py
neuralcli/__init__.py
neuralcli/__main__.py
neuralcli/cli.py
neuralcli/neuralnet.py
neuralcli/writer.py
neuralcli.egg-info/PKG-INFO
neuralcli.egg-info/SOURCES.txt
neuralcli.egg-info/dependency_links.txt
neuralcli.egg-info/entry_points.txt
neuralcli.egg-info/requires.txt
neuralcli.egg-info/top_level.txt