Metadata-Version: 1.1
Name: neuralcli
Version: 1.6
Summary: A command line neural network
Home-page: https://github.com/hugorut/neural-cli
Author: Hugo Rut
Author-email: hugorut@gmail.com
License: UNKNOWN
Download-URL: https://github.com/hugorut/neural-cli/tarball/1.6
Keywords: machine learning,ai,neural nework
Platform: UNKNOWN
